{
  "individual_shapes": [
    {
      "type": "rectangle",
      "x": 25791.4375,
      "y": 6257.7539,
      "width": 529.6417,
      "height": 273.4863,
      "area_sqrt": 380.59,
      "text": "",
      "id": "",
      "class": "",
      "fill": "#999999",
      "stroke": ""
    },
    {
      "type": "rectangle",
      "x": 21053.9375,
      "y": 6257.7539,
      "width": 529.6417,
      "height": 273.4863,
      "area_sqrt": 380.59,
      "text": "",
      "id": "",
      "class": "",
      "fill": "#999999",
      "stroke": ""
    },
    {
      "type": "rectangle",
      "x": 22207.0625,
      "y": 6257.7539,
      "width": 529.6417,
      "height": 273.4863,
      "area_sqrt": 380.59,
      "text": "",
      "id": "",
      "class": "",
      "fill": "#999999",
      "stroke": ""
    },
    {
      "type": "rectangle",
      "x": 24638.3125,
      "y": 6257.7539,
      "width": 529.6417,
      "height": 273.4863,
      "area_sqrt": 380.59,
      "text": "",
      "id": "",
      "class": "",
      "fill": "#999999",
      "stroke": ""
    },
    {
      "type": "rectangle",
      "x": 18747.6875,
      "y": 6257.7539,
      "width": 529.6417,
      "height": 273.4863,
      "area_sqrt": 380.59,
      "text": "",
      "id": "",
      "class": "",
      "fill": "#999999",
      "stroke": ""
    },
    {
      "type": "rectangle",
      "x": 19900.8125,
      "y": 6257.7539,
      "width": 529.6417,
      "height": 273.4863,
      "area_sqrt": 380.59,
      "text": "",
      "id": "",
      "class": "",
      "fill": "#999999",
      "stroke": ""
    },
    {
      "type": "rectangle",
      "x": 11274.7188,
      "y": 10168.1602,
      "width": 488.0585,
      "height": 317.1387,
      "area_sqrt": 393.42,
      "text": "",
      "id": "",
      "class": "",
      "fill": "#2D314A",
      "stroke": ""
    },
    {
      "type": "rectangle",
      "x": 1971.8125,
      "y": 10168.1602,
      "width": 493.8965,
      "height": 317.1387,
      "area_sqrt": 395.77,
      "text": "",
      "id": "",
      "class": "",
      "fill": "#2D314A",
      "stroke": ""
    },
    {
      "type": "rectangle",
      "x": 10681.6875,
      "y": 9175.0977,
      "width": 461.6211,
      "height": 368.0664,
      "area_sqrt": 412.2,
      "text": "",
      "id": "",
      "class": "",
      "fill": "#2D314A",
      "stroke": ""
    },
    {
      "type": "rectangle",
      "x": 15627.8438,
      "y": 8232.9727,
      "width": 538.0615,
      "height": 317.1387,
      "area_sqrt": 413.09,
      "text": "",
      "id": "",
      "class": "",
      "fill": "#2D314A",
      "stroke": ""
    },
    {
      "type": "rectangle",
      "x": 26947.25,
      "y": 6257.7539,
      "width": 642.9993,
      "height": 273.4863,
      "area_sqrt": 419.35,
      "text": "",
      "id": "",
      "class": "",
      "fill": "#999999",
      "stroke": ""
    },
    {
      "type": "rectangle",
      "x": 23362.2188,
      "y": 6257.7539,
      "width": 650.5402,
      "height": 273.4863,
      "area_sqrt": 421.8,
      "text": "",
      "id": "",
      "class": "",
      "fill": "#999999",
      "stroke": ""
    },
    {
      "type": "rectangle",
      "x": 766.2813,
      "y": 11124.3789,
      "width": 567.4072,
      "height": 317.1387,
      "area_sqrt": 424.2,
      "text": "",
      "id": "",
      "class": "",
      "fill": "#2D314A",
      "stroke": ""
    },
    {
      "type": "rectangle",
      "x": 5684.4063,
      "y": 5181.0039,
      "width": 481.2012,
      "height": 375.3418,
      "area_sqrt": 424.99,
      "text": "",
      "id": "",
      "class": "",
      "fill": "#2D314A",
      "stroke": ""
    },
    {
      "type": "rectangle",
      "x": 15620.9375,
      "y": 7261.7227,
      "width": 570.6055,
      "height": 317.1387,
      "area_sqrt": 425.4,
      "text": "",
      "id": "",
      "class": "",
      "fill": "#2D314A",
      "stroke": ""
    },
    {
      "type": "rectangle",
      "x": 15602.2188,
      "y": 10168.1602,
      "width": 583.0353,
      "height": 317.1387,
      "area_sqrt": 430.0,
      "text": "",
      "id": "",
      "class": "",
      "fill": "#2D314A",
      "stroke": ""
    },
    {
      "type": "rectangle",
      "x": 5594.6875,
      "y": 4213.4102,
      "width": 585.6201,
      "height": 317.1387,
      "area_sqrt": 430.96,
      "text": "",
      "id": "",
      "class": "",
      "fill": "#2D314A",
      "stroke": ""
    },
    {
      "type": "rectangle",
      "x": 10063.4375,
      "y": 10168.1602,
      "width": 585.6201,
      "height": 317.1387,
      "area_sqrt": 430.96,
      "text": "",
      "id": "",
      "class": "",
      "fill": "#2D314A",
      "stroke": ""
    },
    {
      "type": "rectangle",
      "x": 1369.5,
      "y": 1259.6602,
      "width": 511.0016,
      "height": 368.0664,
      "area_sqrt": 433.68,
      "text": "",
      "id": "",
      "class": "",
      "fill": "#2D314A",
      "stroke": ""
    },
    {
      "type": "rectangle",
      "x": 751.9688,
      "y": 10168.1602,
      "width": 596.0449,
      "height": 317.1387,
      "area_sqrt": 434.77,
      "text": "",
      "id": "",
      "class": "",
      "fill": "#2D314A",
      "stroke": ""
    },
    {
      "type": "rectangle",
      "x": 3089.8125,
      "y": 10168.1602,
      "width": 601.5991,
      "height": 317.1387,
      "area_sqrt": 436.8,
      "text": "",
      "id": "",
      "class": "",
      "fill": "#2D314A",
      "stroke": ""
    },
    {
      "type": "rectangle",
      "x": 6803.7813,
      "y": 4213.4102,
      "width": 604.9561,
      "height": 317.1387,
      "area_sqrt": 438.01,
      "text": "",
      "id": "",
      "class": "",
      "fill": "#2D314A",
      "stroke": ""
    },
    {
      "type": "rectangle",
      "x": 15584.9375,
      "y": 9200.5664,
      "width": 605.1025,
      "height": 317.1387,
      "area_sqrt": 438.07,
      "text": "",
      "id": "",
      "class": "",
      "fill": "#2D314A",
      "stroke": ""
    },
    {
      "type": "rectangle",
      "x": 6790.875,
      "y": 5210.0977,
      "width": 618.2617,
      "height": 317.1387,
      "area_sqrt": 442.8,
      "text": "",
      "id": "",
      "class": "",
      "fill": "#2D314A",
      "stroke": ""
    },
    {
      "type": "rectangle",
      "x": 10600.0,
      "y": 8232.9727,
      "width": 624.9756,
      "height": 317.1387,
      "area_sqrt": 445.2,
      "text": "",
      "id": "",
      "class": "",
      "fill": "#2D314A",
      "stroke": ""
    },
    {
      "type": "rectangle",
      "x": 3794.0937,
      "y": 1285.1289,
      "width": 643.042,
      "height": 317.1387,
      "area_sqrt": 451.59,
      "text": "",
      "id": "",
      "class": "",
      "fill": "#2D314A",
      "stroke": ""
    },
    {
      "type": "rectangle",
      "x": 1898.875,
      "y": 4187.9414,
      "width": 558.4717,
      "height": 368.0664,
      "area_sqrt": 453.38,
      "text": "",
      "id": "",
      "class": "",
      "fill": "#2D314A",
      "stroke": ""
    },
    {
      "type": "rectangle",
      "x": 4395.6875,
      "y": 7232.6289,
      "width": 552.4017,
      "height": 375.3418,
      "area_sqrt": 455.35,
      "text": "",
      "id": "",
      "class": "",
      "fill": "#2D314A",
      "stroke": ""
    },
    {
      "type": "rectangle",
      "x": 1901.2813,
      "y": 3245.7852,
      "width": 659.9609,
      "height": 317.1387,
      "area_sqrt": 457.49,
      "text": "",
      "id": "",
      "class": "",
      "fill": "#2D314A",
      "stroke": ""
    },
    {
      "type": "rectangle",
      "x": 2505.375,
      "y": 1285.1289,
      "width": 664.2548,
      "height": 317.1387,
      "area_sqrt": 458.98,
      "text": "",
      "id": "",
      "class": "",
      "fill": "#2D314A",
      "stroke": ""
    },
    {
      "type": "rectangle",
      "x": 4395.75,
      "y": 5210.0977,
      "width": 664.7461,
      "height": 317.1387,
      "area_sqrt": 459.15,
      "text": "",
      "id": "",
      "class": "",
      "fill": "#2D314A",
      "stroke": ""
    },
    {
      "type": "rectangle",
      "x": 67.625,
      "y": 1285.1289,
      "width": 677.2644,
      "height": 317.1387,
      "area_sqrt": 463.45,
      "text": "",
      "id": "",
      "class": "",
      "fill": "#2D314A",
      "stroke": ""
    },
    {
      "type": "rectangle",
      "x": 5029.5938,
      "y": 6181.3477,
      "width": 528.2959,
      "height": 426.2695,
      "area_sqrt": 474.55,
      "text": "",
      "id": "",
      "class": "",
      "fill": "#2D314A",
      "stroke": ""
    },
    {
      "type": "rectangle",
      "x": 1921.8438,
      "y": 2252.7227,
      "width": 618.8385,
      "height": 368.0664,
      "area_sqrt": 477.26,
      "text": "",
      "id": "",
      "class": "",
      "fill": "#2D314A",
      "stroke": ""
    },
    {
      "type": "rectangle",
      "x": 3845.1563,
      "y": 185.7227,
      "width": 540.9668,
      "height": 423.4863,
      "area_sqrt": 478.64,
      "text": "",
      "id": "",
      "class": "",
      "fill": "#08427B",
      "stroke": ""
    },
    {
      "type": "rectangle",
      "x": 721.25,
      "y": 160.2539,
      "width": 557.5073,
      "height": 474.4141,
      "area_sqrt": 514.29,
      "text": "",
      "id": "",
      "class": "",
      "fill": "#08427B",
      "stroke": ""
    },
    {
      "type": "rectangle",
      "x": 2497.6875,
      "y": 185.7227,
      "width": 679.6143,
      "height": 423.4863,
      "area_sqrt": 536.48,
      "text": "",
      "id": "",
      "class": "",
      "fill": "#08427B",
      "stroke": ""
    }
  ],
  "groups": [
    {
      "type": "group",
      "x": 25791.4375,
      "y": 6257.7539,
      "width": 529.6417,
      "height": 273.4863,
      "area_sqrt": 380.59,
      "text": "\u00abexternal_system\u00bb SAP Planet 8/9 ERP System",
      "id": "entity_sap_planet",
      "class": "entity",
      "data_entity": "sap_planet",
      "data_uid": "ent0006"
    },
    {
      "type": "group",
      "x": 21053.9375,
      "y": 6257.7539,
      "width": 529.6417,
      "height": 273.4863,
      "area_sqrt": 380.59,
      "text": "\u00abexternal_system\u00bb Cherwell HR HR Management",
      "id": "entity_cherwell_hr",
      "class": "entity",
      "data_entity": "cherwell_hr",
      "data_uid": "ent0007"
    },
    {
      "type": "group",
      "x": 22207.0625,
      "y": 6257.7539,
      "width": 529.6417,
      "height": 273.4863,
      "area_sqrt": 380.59,
      "text": "\u00abexternal_system\u00bb Power Apps Low-code Platform",
      "id": "entity_power_apps",
      "class": "entity",
      "data_entity": "power_apps",
      "data_uid": "ent0009"
    },
    {
      "type": "group",
      "x": 24638.3125,
      "y": 6257.7539,
      "width": 529.6417,
      "height": 273.4863,
      "area_sqrt": 380.59,
      "text": "\u00abexternal_system\u00bb Microsoft Teams Communication",
      "id": "entity_teams",
      "class": "entity",
      "data_entity": "teams",
      "data_uid": "ent0011"
    },
    {
      "type": "group",
      "x": 18747.6875,
      "y": 6257.7539,
      "width": 529.6417,
      "height": 273.4863,
      "area_sqrt": 380.59,
      "text": "\u00abexternal_system\u00bb Azure AD Identity Provider",
      "id": "entity_azure_ad",
      "class": "entity",
      "data_entity": "azure_ad",
      "data_uid": "ent0012"
    },
    {
      "type": "group",
      "x": 19900.8125,
      "y": 6257.7539,
      "width": 529.6417,
      "height": 273.4863,
      "area_sqrt": 380.59,
      "text": "\u00abexternal_system\u00bb Azure Data Lake Data Storage",
      "id": "entity_data_lake",
      "class": "entity",
      "data_entity": "data_lake",
      "data_uid": "ent0013"
    },
    {
      "type": "group",
      "x": 11274.7188,
      "y": 10168.1602,
      "width": 488.0585,
      "height": 317.1387,
      "area_sqrt": 393.42,
      "text": "\u00abcontainer\u00bb ML Platform [ML] Machine learning",
      "id": "entity_ml_platform",
      "class": "entity",
      "data_entity": "ml_platform",
      "data_uid": "ent0050"
    },
    {
      "type": "group",
      "x": 1971.8125,
      "y": 10168.1602,
      "width": 493.8965,
      "height": 317.1387,
      "area_sqrt": 395.77,
      "text": "\u00abcontainer\u00bb Backup Service [.NET Core] Data protection",
      "id": "entity_backup_service",
      "class": "entity",
      "data_entity": "backup_service",
      "data_uid": "ent0034"
    },
    {
      "type": "group",
      "x": 10681.6875,
      "y": 9175.0977,
      "width": 461.6211,
      "height": 368.0664,
      "area_sqrt": 412.2,
      "text": "\u00abcontainer\u00bb Azure Monitor [Monitor] Infrastructure monitoring",
      "id": "entity_azure_monitor",
      "class": "entity",
      "data_entity": "azure_monitor",
      "data_uid": "ent0048"
    },
    {
      "type": "group",
      "x": 15627.8438,
      "y": 8232.9727,
      "width": 538.0615,
      "height": 317.1387,
      "area_sqrt": 413.09,
      "text": "\u00abcontainer\u00bb Azure Event Grid [Event Grid] Event routing",
      "id": "entity_event_grid",
      "class": "entity",
      "data_entity": "event_grid",
      "data_uid": "ent0038"
    },
    {
      "type": "group",
      "x": 26947.25,
      "y": 6257.7539,
      "width": 642.9993,
      "height": 273.4863,
      "area_sqrt": 419.35,
      "text": "\u00abexternal_system\u00bb Cherwell IT IT Service Management",
      "id": "entity_cherwell_it",
      "class": "entity",
      "data_entity": "cherwell_it",
      "data_uid": "ent0008"
    },
    {
      "type": "group",
      "x": 23362.2188,
      "y": 6257.7539,
      "width": 650.5402,
      "height": 273.4863,
      "area_sqrt": 421.8,
      "text": "\u00abexternal_system\u00bb SharePoint Document Management",
      "id": "entity_sharepoint",
      "class": "entity",
      "data_entity": "sharepoint",
      "data_uid": "ent0010"
    },
    {
      "type": "group",
      "x": 766.2813,
      "y": 11124.3789,
      "width": 567.4072,
      "height": 317.1387,
      "area_sqrt": 424.2,
      "text": "\u00abcontainer\u00bb Reporting Service [.NET Core] Business reports",
      "id": "entity_reporting_service",
      "class": "entity",
      "data_entity": "reporting_service",
      "data_uid": "ent0035"
    },
    {
      "type": "group",
      "x": 5684.4063,
      "y": 5181.0039,
      "width": 481.2012,
      "height": 375.3418,
      "area_sqrt": 424.99,
      "text": "\u00abcontainer\u00bb Authentication Service [.NET Core] OAuth 2.0 & JWT",
      "id": "entity_auth_service",
      "class": "entity",
      "data_entity": "auth_service",
      "data_uid": "ent0024"
    },
    {
      "type": "group",
      "x": 15620.9375,
      "y": 7261.7227,
      "width": 570.6055,
      "height": 317.1387,
      "area_sqrt": 425.4,
      "text": "\u00abcontainer\u00bb Azure Service Bus [Service Bus] Message queuing",
      "id": "entity_service_bus",
      "class": "entity",
      "data_entity": "service_bus",
      "data_uid": "ent0037"
    },
    {
      "type": "group",
      "x": 15602.2188,
      "y": 10168.1602,
      "width": 583.0353,
      "height": 317.1387,
      "area_sqrt": 430.0,
      "text": "\u00abcontainer\u00bb Stream Analytics [Stream] Real-time processing",
      "id": "entity_stream_analytics",
      "class": "entity",
      "data_entity": "stream_analytics",
      "data_uid": "ent0040"
    },
    {
      "type": "group",
      "x": 5594.6875,
      "y": 4213.4102,
      "width": 585.6201,
      "height": 317.1387,
      "area_sqrt": 430.96,
      "text": "\u00abcontainer\u00bb Analytics Service [.NET Core] Business intelligence",
      "id": "entity_analytics_service",
      "class": "entity",
      "data_entity": "analytics_service",
      "data_uid": "ent0027"
    },
    {
      "type": "group",
      "x": 10063.4375,
      "y": 10168.1602,
      "width": 585.6201,
      "height": 317.1387,
      "area_sqrt": 430.96,
      "text": "\u00abcontainer\u00bb Power BI [Power BI] Business intelligence",
      "id": "entity_power_bi",
      "class": "entity",
      "data_entity": "power_bi",
      "data_uid": "ent0049"
    },
    {
      "type": "group",
      "x": 1369.5,
      "y": 1259.6602,
      "width": 511.0016,
      "height": 368.0664,
      "area_sqrt": 433.68,
      "text": "\u00abcontainer\u00bb Angular Portal [Angular] Unified enterprise interface",
      "id": "entity_angular_portal",
      "class": "entity",
      "data_entity": "angular_portal",
      "data_uid": "ent0015"
    },
    {
      "type": "group",
      "x": 751.9688,
      "y": 10168.1602,
      "width": 596.0449,
      "height": 317.1387,
      "area_sqrt": 434.77,
      "text": "\u00abcontainer\u00bb Monitoring Service [.NET Core] Health checks",
      "id": "entity_monitoring_service",
      "class": "entity",
      "data_entity": "monitoring_service",
      "data_uid": "ent0033"
    },
    {
      "type": "group",
      "x": 3089.8125,
      "y": 10168.1602,
      "width": 601.5991,
      "height": 317.1387,
      "area_sqrt": 436.8,
      "text": "\u00abcontainer\u00bb Audit Service [.NET Core] Compliance & logging",
      "id": "entity_audit_service",
      "class": "entity",
      "data_entity": "audit_service",
      "data_uid": "ent0032"
    },
    {
      "type": "group",
      "x": 6803.7813,
      "y": 4213.4102,
      "width": 604.9561,
      "height": 317.1387,
      "area_sqrt": 438.01,
      "text": "\u00abcontainer\u00bb Integration Service [.NET Core] System integrations",
      "id": "entity_integration_service",
      "class": "entity",
      "data_entity": "integration_service",
      "data_uid": "ent0028"
    },
    {
      "type": "group",
      "x": 15584.9375,
      "y": 9200.5664,
      "width": 605.1025,
      "height": 317.1387,
      "area_sqrt": 438.07,
      "text": "\u00abcontainer\u00bb Azure Functions [Functions] Serverless processing",
      "id": "entity_azure_functions",
      "class": "entity",
      "data_entity": "azure_functions",
      "data_uid": "ent0039"
    },
    {
      "type": "group",
      "x": 6790.875,
      "y": 5210.0977,
      "width": 618.2617,
      "height": 317.1387,
      "area_sqrt": 442.8,
      "text": "\u00abcontainer\u00bb Notification Service [.NET Core] Multi-channel alerts",
      "id": "entity_notification_service",
      "class": "entity",
      "data_entity": "notification_service",
      "data_uid": "ent0029"
    },
    {
      "type": "group",
      "x": 10600.0,
      "y": 8232.9727,
      "width": 624.9756,
      "height": 317.1387,
      "area_sqrt": 445.2,
      "text": "\u00abcontainer\u00bb Application Insights [App Insights] Application telemetry",
      "id": "entity_app_insights",
      "class": "entity",
      "data_entity": "app_insights",
      "data_uid": "ent0047"
    },
    {
      "type": "group",
      "x": 3794.0937,
      "y": 1285.1289,
      "width": 643.042,
      "height": 317.1387,
      "area_sqrt": 451.59,
      "text": "\u00abcontainer\u00bb Analytics Dashboard [Angular] Business intelligence",
      "id": "entity_analytics_dashboard",
      "class": "entity",
      "data_entity": "analytics_dashboard",
      "data_uid": "ent0018"
    },
    {
      "type": "group",
      "x": 1898.875,
      "y": 4187.9414,
      "width": 558.4717,
      "height": 368.0664,
      "area_sqrt": 453.38,
      "text": "\u00abcontainer\u00bb Security Gateway [Security] OAuth 2.0 & JWT validation",
      "id": "entity_security_gateway",
      "class": "entity",
      "data_entity": "security_gateway",
      "data_uid": "ent0022"
    },
    {
      "type": "group",
      "x": 4395.6875,
      "y": 7232.6289,
      "width": 552.4017,
      "height": 375.3418,
      "area_sqrt": 455.35,
      "text": "\u00abcontainer\u00bb IT Service Management [.NET Core] IT support & tickets",
      "id": "entity_it_service",
      "class": "entity",
      "data_entity": "it_service",
      "data_uid": "ent0026"
    },
    {
      "type": "group",
      "x": 1901.2813,
      "y": 3245.7852,
      "width": 659.9609,
      "height": 317.1387,
      "area_sqrt": 457.49,
      "text": "\u00abcontainer\u00bb Application Gateway [App GW] Load balancer & routing",
      "id": "entity_app_gateway",
      "class": "entity",
      "data_entity": "app_gateway",
      "data_uid": "ent0021"
    },
    {
      "type": "group",
      "x": 2505.375,
      "y": 1285.1289,
      "width": 664.2548,
      "height": 317.1387,
      "area_sqrt": 458.98,
      "text": "\u00abcontainer\u00bb Admin Dashboard [Angular] Administrative interface",
      "id": "entity_admin_dashboard",
      "class": "entity",
      "data_entity": "admin_dashboard",
      "data_uid": "ent0017"
    },
    {
      "type": "group",
      "x": 4395.75,
      "y": 5210.0977,
      "width": 664.7461,
      "height": 317.1387,
      "area_sqrt": 459.15,
      "text": "\u00abcontainer\u00bb Saga Orchestrator [.NET Core] Distributed transactions",
      "id": "entity_saga_orchestrator",
      "class": "entity",
      "data_entity": "saga_orchestrator",
      "data_uid": "ent0030"
    },
    {
      "type": "group",
      "x": 67.625,
      "y": 1285.1289,
      "width": 677.2644,
      "height": 317.1387,
      "area_sqrt": 463.45,
      "text": "\u00abcontainer\u00bb Mobile PWA [Angular PWA] Mobile enterprise access",
      "id": "entity_mobile_pwa",
      "class": "entity",
      "data_entity": "mobile_pwa",
      "data_uid": "ent0016"
    },
    {
      "type": "group",
      "x": 5029.5938,
      "y": 6181.3477,
      "width": 528.2959,
      "height": 426.2695,
      "area_sqrt": 474.55,
      "text": "\u00abcontainer\u00bb HR Management Service [.NET Core] Employee data & workflows",
      "id": "entity_hr_service",
      "class": "entity",
      "data_entity": "hr_service",
      "data_uid": "ent0025"
    },
    {
      "type": "group",
      "x": 1921.8438,
      "y": 2252.7227,
      "width": 618.8385,
      "height": 368.0664,
      "area_sqrt": 477.26,
      "text": "\u00abcontainer\u00bb API Management [APIM] API gateway with ARM templates",
      "id": "entity_api_management",
      "class": "entity",
      "data_entity": "api_management",
      "data_uid": "ent0020"
    },
    {
      "type": "group",
      "x": 3845.1563,
      "y": 185.7227,
      "width": 540.9668,
      "height": 423.4863,
      "area_sqrt": 478.64,
      "text": "\u00abperson\u00bb Business Analyst Views analytics",
      "id": "entity_analyst",
      "class": "entity",
      "data_entity": "analyst",
      "data_uid": "ent0004"
    },
    {
      "type": "group",
      "x": 721.25,
      "y": 160.2539,
      "width": 557.5073,
      "height": 474.4141,
      "area_sqrt": 514.29,
      "text": "\u00abperson\u00bb BAT Employee Accesses enterprise systems",
      "id": "entity_employee",
      "class": "entity",
      "data_entity": "employee",
      "data_uid": "ent0002"
    },
    {
      "type": "group",
      "x": 2497.6875,
      "y": 185.7227,
      "width": 679.6143,
      "height": 423.4863,
      "area_sqrt": 536.48,
      "text": "\u00abperson\u00bb System Administrator Manages platform",
      "id": "entity_admin",
      "class": "entity",
      "data_entity": "admin",
      "data_uid": "ent0003"
    },
    {
      "type": "group",
      "x": 0.0,
      "y": 0.0,
      "width": 27681.25,
      "height": 11856.25,
      "area_sqrt": 18116.18,
      "text": "",
      "id": "",
      "class": "",
      "data_entity": "",
      "data_uid": ""
    }
  ],
  "total_shapes": 37,
  "total_groups": 38,
  "expected_shapes": 41,
  "expected_groups": 8
}